ab12phylo/__init__.py
ab12phylo/ab12phylo_app.py
ab12phylo/ab12phylo_init.py
ab12phylo/gtk_base.py
ab12phylo/gtk_blast.py
ab12phylo/gtk_gbl.py
ab12phylo/gtk_io.py
ab12phylo/gtk_ml.py
ab12phylo/gtk_msa.py
ab12phylo/gtk_proj.py
ab12phylo/gtk_qal.py
ab12phylo/gtk_rgx.py
ab12phylo/gtk_tree.py
ab12phylo/repo.py
ab12phylo/files/align.png
ab12phylo/files/anno.png
ab12phylo/files/axis.png
ab12phylo/files/circ.png
ab12phylo/files/favi.ico
ab12phylo/files/favi.png
ab12phylo/files/favi.svg
ab12phylo/files/fbp.png
ab12phylo/files/flip.png
ab12phylo/files/floppy.png
ab12phylo/files/gui.glade
ab12phylo/files/html.png
ab12phylo/files/mindist.png
ab12phylo/files/msa.png
ab12phylo/files/nwk.png
ab12phylo/files/pdf.png
ab12phylo/files/png.png
ab12phylo/files/rect.png
ab12phylo/files/space.png
ab12phylo/files/spec.png
ab12phylo/files/supp.png
ab12phylo/files/svg.png
ab12phylo/files/tbe.png
ab12phylo/files/unro.png
ab12phylo_cmd/__init__.py
ab12phylo_cmd/blast.py
ab12phylo_cmd/cli.py
ab12phylo_cmd/filter.py
ab12phylo_cmd/i_o.py
ab12phylo_cmd/main.py
ab12phylo_cmd/ml.py
ab12phylo_cmd/msa.py
ab12phylo_cmd/phylo.py
ab12phylo_cmd/template.jinja
ab12phylo_cmd/cgi-bin/ab12phylo.py
ab12phylo_cmd/cgi-bin/favicon.ico
ab12phylo_cmd/cgi-bin/favicon.png
ab12phylo_cmd/config/config.yaml
ab12phylo_cmd/config/test_config.yaml
ab12phylo_cmd/tools/Gblocks_0.91b/Gblocks
ab12phylo_cmd/tools/Gblocks_0.91b/Gblocks.exe
ab12phylo_cmd/tools/Gblocks_0.91b/nad3.pir
ab12phylo_cmd/tools/Gblocks_0.91b/paths
ab12phylo_cmd/tools/Gblocks_0.91b/more_alignments/cox2.pir
ab12phylo_cmd/tools/Gblocks_0.91b/more_alignments/cytb.pir
ab12phylo_cmd/tools/Gblocks_0.91b/more_alignments/nad3.pir
ab12phylo_cmd/tools/Gblocks_0.91b/more_alignments/nad5.pir
ab12phylo_cmd/tools/MSA_clients/clustalo.py
ab12phylo_cmd/tools/MSA_clients/mafft.py
ab12phylo_cmd/tools/MSA_clients/muscle.py
ab12phylo_cmd/tools/MSA_clients/tcoffee.py
ab12phylo_cmd/tools/mview-1.67/CHANGES
ab12phylo_cmd/tools/mview-1.67/LICENSE.md
ab12phylo-0.5.21b0.dist-info/LICENSE.md
ab12phylo-0.5.21b0.dist-info/METADATA
ab12phylo-0.5.21b0.dist-info/WHEEL
ab12phylo-0.5.21b0.dist-info/entry_points.txt
ab12phylo-0.5.21b0.dist-info/top_level.txt
ab12phylo-0.5.21b0.dist-info/RECORD
