Metadata-Version: 2.1
Name: ab12phylo
Version: 0.5.21b0
Summary: Integrated pipeline for ML phylogenetic inference from ABI trace and FASTA data
Home-page: https://github.com/lkndl/ab12phylo
Author: Leo Kaindl
Author-email: leo.kaindl@tum.de
License: gpl-3.0
Keywords: bioinformatics,phylogenetics,population genetics
Platform: any
Classifier: Development Status :: 4 - Beta
Classifier: Programming Language :: Python :: 3.6
Classifier: License :: OSI Approved :: GNU General Public License v3 (GPLv3)
Classifier: Operating System :: OS Independent
Requires-Python: >=3.6
License-File: LICENSE.md
Requires-Dist: biopython
Requires-Dist: pyyaml
Requires-Dist: jinja2
Requires-Dist: lxml
Requires-Dist: xmltramp2
Requires-Dist: toyplot
Requires-Dist: toytree (<=1.2.0)
Requires-Dist: numpy
Requires-Dist: pandas
Requires-Dist: matplotlib
Requires-Dist: svgutils
Requires-Dist: pillow
Requires-Dist: requests
Requires-Dist: importlib-metadata
Requires-Dist: keyring
Requires-Dist: beautifulsoup4
